{
  "kind": "singleType",
  "collectionName": "organization_of_work_data",
  "info": {
    "name": "organizationOfWorkData"
  },
  "options": {
    "increments": true,
    "timestamps": true,
    "draftAndPublish": true
  },
  "pluginOptions": {
    "i18n": {
      "localized": true
    }
  },
  "attributes": {
    "header": {
      "pluginOptions": {
        "i18n": {
          "localized": true
        }
      },
      "type": "string"
    },
    "items": {
      "type": "component",
      "repeatable": true,
      "pluginOptions": {
        "i18n": {
          "localized": true
        }
      },
      "component": "components.organization-of-work-data-item"
    },
    "photo": {
      "type": "component",
      "repeatable": false,
      "pluginOptions": {
        "i18n": {
          "localized": true
        }
      },
      "component": "components.img"
    },
    "quote": {
      "pluginOptions": {
        "i18n": {
          "localized": true
        }
      },
      "type": "richtext"
    },
    "signature": {
      "pluginOptions": {
        "i18n": {
          "localized": true
        }
      },
      "type": "text"
    }
  }
}
